acquisition_sanitizer/__init__.py
acquisition_sanitizer/sc_decision.py
acquisition_sanitizer-0.4.1.dist-info/WHEEL
acquisition_sanitizer-0.4.1.dist-info/METADATA
acquisition_sanitizer-0.4.1.dist-info/RECORD
