Metadata-Version: 2.1
Name: acquisition-sanitizer
Version: 0.4.1
Summary: Clean scraped decisions for better pattern matching.
Author: Marcelino G. Veloso III
Author-email: mars@veloso.one
Requires-Python: >=3.9,<4.0
Classifier: Programming Language :: Python :: 3
Classifier: Programming Language :: Python :: 3.9
Classifier: Programming Language :: Python :: 3.10
Requires-Dist: html-sanitizer (>=1.9.3,<2.0.0)
